{
    "chapters":{
        "1":{
            "author_id":"babyrouge7x",
            "author_name":"Amy",
            "choices":[
                "Hypno Ray ",
                "Time machine ",
                "Youth potion ",
                "Diaper",
                "Other"
            ],
            "content":"<div class=\"\"><div> <span>Tails was in his lab working on his latest invention. Well, maybe this one being his latest was a understatement. He had created many new inventions over the last few days. It seemed his brain was coming up with ideas faster then ever. But he had made so many inventions that he didn't have time to test them. He had just finished the machine he was working on. He looked at his inventions and sighed. \"How am I ever going to test all of these?\" He said. <br>\r\n<br>\r\nSuddenly his alarm system went off. \"Intruder detected in vault.\" Said his security system. Tails ran to his vault where he kept his valuables such as rings, and chaos emeralds. When he got there he opened the door to find none other then Rouge. \"Rouge? what are you doing here?\" He said. \"What also would a master thief be doing in a vault?\" Said Rouge. \"But I can see This was a waste of time. There's nothing in here.\" Yes the vault was empty. But it was a security feature Tails had made. The vault was designed to teleport what ever was inside it to a empty dimension where no thief could get to it. and it could only be activated by Tails voice. <br>\r\n<br>\r\nThen Tails had a Idea. \"You came here for the chaos emerald didn't you?\" He asked, knowing the answer. \"No duh, Sherlock.\" Said Rouge. \"Well, How about we make a deal? I have some inventions I haven't tested yet. If you help me test them, I'll give you the chaos emerald.\" Rouge thought about it. She decided it was the only way to get the emerald. \"All right, I'll do it.\" She said. She followed Tails to the main part of the lab where he kept his most recent inventions. \"What should I test first?\" He thought.</span></div></div>",
            "created":1582520400,
            "id":2792460,
            "title":"Opening"
        },
        "11":{
            "author_id":"babyrouge7x",
            "author_name":"Amy",
            "choices":[
                "Made her think she was a baby",
                "Made her a slave",
                "Add triggers",
                "Made her a chicken ",
                "Other"
            ],
            "content":"<div class=\"\"><span style=\"font-size:1.47em;\"><div> <span>Tails then shoots Rouge with the hypno ray. Suddenly Rouges face went blank and she drooled a little<br>\r\n<br>\r\nTails then</span></div></span></div>",
            "created":1582606800,
            "id":2792633,
            "title":"Hypno Ray "
        },
        "111":{
            "author_id":"babyrouge7x",
            "author_name":"Amy",
            "choices":[
                "Newborn ",
                "1",
                "2"
            ],
            "content":"<div class=\"\"><span style=\"font-size:1.47em;\"><div> <span>What age? </span></div></span></div>",
            "created":1582606800,
            "id":2792634,
            "title":"Child\u2019s play"
        },
        "1111":{
            "author_id":"babyrouge7x",
            "author_name":"Amy",
            "choices":[
                "Gave her a bath",
                "Used a different invention ",
                "Other"
            ],
            "content":"<div class=\"\"><span style=\"font-size:1.47em;\"><div> <span>Rouge then fell on her bum and started to suck her thumb. Tails smiled at the bat but that smile soon disappeared as he smelled a foul smell. \u201cPew, what a stinky baby!\u201d Tails exclaimed. He then</span></div></span></div>",
            "created":1582606800,
            "id":2792670,
            "title":"Tiny little Rouge"
        },
        "11111":{
            "author_id":"babyrouge7x",
            "author_name":"Amy",
            "choices":[
                "The end",
                "Go to the park",
                "Other"
            ],
            "content":"<div class=\"\"><div> <span>Tails then bathed Rouge as she babbled nonsense. Once clean Tails dried her off and powdered her. Rouge giggled as she felt the thick diaper being put on her. Tails then put a bonnet on her and gave her a rattle. Much to Rouges enjoyment she shook the rattle happily.</span></div></div>",
            "created":1582606800,
            "id":2792673,
            "title":"Gave her a bath"
        },
        "111111":{
            "author_id":"babyrouge7x",
            "author_name":"Amy",
            "choices":null,
            "content":"<div class=\"\"><span style=\"font-size:1.47em;\"><div> <span>Tails then tucked rouge into her new crib and turned a chaos emerald themed mobile on. Rouge reaches for it a little bit but after a few mins she was out cold.<br>\r\n<br>\r\n<br>\r\nThe end</span></div></span></div>",
            "created":1582606800,
            "id":2792676,
            "title":"The end"
        },
        "11113":{
            "author_id":"babyrouge7x",
            "author_name":"Amy",
            "choices":[
                "Turn her back",
                "Drop her off somewhere",
                "Other"
            ],
            "content":"<div class=\"\"><span style=\"font-size:1.47em;\"><div> <span>What else?</span></div></span></div>",
            "created":1582606800,
            "id":2792706,
            "title":"Other"
        },
        "111133":{
            "author_id":"babyrouge7x",
            "author_name":"Amy",
            "choices":[
                "Take her to the mall",
                "Feed her",
                "Other"
            ],
            "content":"<div class=\"\"><span style=\"font-size:1.47em;\"><div> <span>What else again</span></div></span></div>",
            "created":1582606800,
            "id":2792707,
            "title":"Other again"
        },
        "113":{
            "author_id":"babyrouge7x",
            "author_name":"Amy",
            "choices":[
                "Bowel/bladder controls",
                "Chicken/gas",
                "Other"
            ],
            "content":"<div class=\"\"><span style=\"font-size:1.47em;\"><div> <span>What\u2019s the triggers?</span></div></span></div>",
            "created":1582606800,
            "id":2792691,
            "title":"triggers added"
        },
        "1132":{
            "author_id":"babyrouge7x",
            "author_name":"Amy",
            "choices":[
                "More hypnosis",
                "Keep snapping",
                "Other"
            ],
            "content":"<div class=\"\"><div> <span>\"Now, when I say \u201cchicken nuggets\u201d  you will.....think your a chicken, chicken nugget!.\" Tails said. For a moment Rouge just stood there. <br>\r\n<br>\r\nThen she started flapping her arms and strutting around going \"Bwok, buck buck buck buck, Bagowk!\" She bent over a started pecking at the floor. \"It worked!\" Said Tails. Then he got another idea. \u201cChicken nugget.\u201d Tails said turning rouge back to normal, though a little confused. \u201cWhen I snap my fingers you will fart\u201d tails said and snapped. Suddenly a loud fart comes from Rouge which causes her to blush. </span></div></div>",
            "created":1582606800,
            "id":2792693,
            "title":"Hypno humiliation "
        },
        "11322":{
            "author_id":"babyrouge7x",
            "author_name":"Amy",
            "choices":[
                "Tease her",
                "Calm her down",
                "Other"
            ],
            "content":"<div class=\"\"><span style=\"font-size:1.47em;\"><div> <span>Tails snapped and snapped as the noises got louder and Rouges face got redder until a bulge appeared in Rouges pants. Rouge burst into tears from in embarrassment  </span></div></span></div>",
            "created":1582606800,
            "id":2792695,
            "title":"An accident "
        },
        "114":{
            "author_id":"babyrouge7x",
            "author_name":"Amy",
            "choices":[
                "Watches Rouge more",
                "Take rouge out into public",
                "Other "
            ],
            "content":"<div class=\"\"><div> <span>Tails then got a idea <br>\r\n<br>\r\n\u201cYou think your a chicken.\" Tails snapped his fingers. For a moment Rouge just stood there. <br>\r\n<br>\r\nThen she started flapping her arms and strutting around going \"Bwok, buck buck buck buck, Bagowk!\" She bent over a started pecking at the floor. Tails bursts into laughter. Tails then\u2026</span></div></div>",
            "created":1582606800,
            "id":2792698,
            "title":"Rouge the chicken "
        },
        "1143":{
            "author_id":"babyrouge7x",
            "author_name":"Amy",
            "choices":[
                "Rouge pees herself",
                "Tails loses Rouge",
                "Other"
            ],
            "content":"<div class=\"\"><span style=\"font-size:1.47em;\"><div> <span>What else?</span></div></span></div>",
            "created":1582606800,
            "id":2792699,
            "title":"Other "
        },
        "115":{
            "author_id":"babyrouge7x",
            "author_name":"Amy",
            "choices":[
                "Makes her love tails ",
                "Makes her Abdl ",
                "Other"
            ],
            "content":"<div class=\"\"><span style=\"font-size:1.47em;\"><div> <span>What else?</span></div></span></div>",
            "created":1582606800,
            "id":2792679,
            "title":"Other"
        },
        "12":{
            "author_id":"babyrouge7x",
            "author_name":"Amy",
            "choices":[
                "Go back in time",
                "Go to the future ",
                "Go back in time (It malfunctions)",
                "Go to the future (It malfunctions)",
                "Other"
            ],
            "content":"<div class=\"\"><span style=\"font-size:1.47em;\"><div> <span>What does she do with it</span></div></span></div>",
            "created":1582520400,
            "id":2792466,
            "title":"Time machine "
        },
        "123":{
            "author_id":"babyrouge7x",
            "author_name":"Amy",
            "choices":[
                "Rouge is younger ",
                "Rouge rewinds time to when she was a baby",
                "Other "
            ],
            "content":"<div class=\"\"><span style=\"font-size:1.47em;\"><div> <span>Rouge stepped into the time machine and tails flipped a switch. Unfortunately sparks started to fly from the machine and fog filled the inside of the time machine. What happend?</span></div></span></div>",
            "created":1582606800,
            "id":2792796,
            "title":"didn\u2019t make it back to the past"
        },
        "1233":{
            "author_id":"babyrouge7x",
            "author_name":"Amy",
            "choices":[
                "Nothing",
                "She\u2019s mentally younger",
                "Other "
            ],
            "content":"<div class=\"\"><span style=\"font-size:1.47em;\"><div> <span>What happend?</span></div></span></div>",
            "created":1582606800,
            "id":2792800,
            "title":"Other"
        },
        "13":{
            "author_id":"babyrouge7x",
            "author_name":"Amy",
            "choices":[
                "Into a newborn ",
                "A one year old",
                "2 year old",
                "3 year old",
                "Other "
            ],
            "content":"<div class=\"\"><span style=\"font-size:1.47em;\"><div> <span>Rouge drinks the potion and she turns </span></div></span></div>",
            "created":1582520400,
            "id":2792472,
            "title":"Youth potion "
        },
        "133":{
            "author_id":"babyrouge7x",
            "author_name":"Amy",
            "choices":[
                "What the fuck!?",
                "Hewwo",
                "Other"
            ],
            "content":"<div class=\"\"><div> <span>\u201cOh my god rouge!\u201d Tails screamed<br>\r\n<br>\r\nThen a small thing came outta the rouge's suit, turns out it was her, but now she's been regressed as a toddler, about two years now, and was probably naked from under the suit.<br>\r\n<br>\r\n\u201c Oh my god, it worked, the machine worked! Rouge, you alright, can you talk to me.\u201d Tails said<br>\r\n<br>\r\nThen, rouge started to say something...</span></div></div>",
            "created":1582606800,
            "id":2792701,
            "title":"2 year old"
        },
        "14":{
            "author_id":"babyrouge7x",
            "author_name":"Amy",
            "choices":[
                "It\u2019s not",
                "It mind controls the user",
                "It grants wishes",
                "It\u2019s magic",
                "Other "
            ],
            "content":"<div class=\"\"><span style=\"font-size:1.47em;\"><div> <span>How was this diaper special?</span></div></span></div>",
            "created":1582606800,
            "id":2792678,
            "title":"Diaper"
        },
        "144":{
            "author_id":"babyrouge7x",
            "author_name":"Amy",
            "choices":[
                "It gives rouge powers ",
                "It makes her a princess ",
                "Other"
            ],
            "content":"<div class=\"\"><span style=\"font-size:1.47em;\"><div> <span>After a very long argument, Tails somehow manages to convince Rouge to put on the diaper. Once on Rouge blushes and pouts a little but then the diaper glows<br>\r\n<br>\r\n<br>\r\nWhat does it do</span></div></span></div>",
            "created":1582606800,
            "id":2792715,
            "title":"magic"
        },
        "1443":{
            "author_id":"babyrouge7x",
            "author_name":"Amy",
            "choices":[
                "It turns her into stone",
                "It makes her need diapers",
                "Other"
            ],
            "content":"<div class=\"\"><span style=\"font-size:1.47em;\"><div> <span>What does it do?</span></div></span></div>",
            "created":1582606800,
            "id":2792718,
            "title":"Other"
        },
        "14431":{
            "author_id":"babyrouge7x",
            "author_name":"Amy",
            "choices":null,
            "content":"<div class=\"\"><span style=\"font-size:1.47em;\"><div> <span>Rouge then turns to stone. Tails, proud of his accomplishment, leaves her there as a trophy.</span></div></span></div>",
            "created":1582606800,
            "id":2792720,
            "title":"Statue ending"
        },
        "14432":{
            "author_id":"babyrouge7x",
            "author_name":"Amy",
            "choices":[
                "Her bladder",
                "Her bowels",
                "Both"
            ],
            "content":"<div class=\"\"><span style=\"font-size:1.47em;\"><div> <span>What can\u2019t she control?</span></div></span></div>",
            "created":1582606800,
            "id":2792723,
            "title":"It makes her need diapers"
        },
        "145":{
            "author_id":"babyrouge7x",
            "author_name":"Amy",
            "choices":[
                "When she uses it she poops gold",
                "It regresses her",
                "Other "
            ],
            "content":"<div class=\"\"><span style=\"font-size:1.47em;\"><div> <span>How is it special </span></div></span></div>",
            "created":1582606800,
            "id":2792783,
            "title":"Special "
        },
        "15":{
            "author_id":"babyrouge7x",
            "author_name":"Amy",
            "choices":[
                "Reality warp device ",
                "Shrink ray ",
                "Mind control helmet ",
                "Transformation watch ",
                "Other"
            ],
            "content":"<div class=\"\"><span style=\"font-size:1.47em;\"><div> <span>What else?</span></div></span></div>",
            "created":1582520400,
            "id":2792462,
            "title":"Other"
        },
        "152":{
            "author_id":"babyrouge7x",
            "author_name":"Amy",
            "choices":[
                "Put her in a baby dolls clothes",
                "Give cream the \u201cdoll\u201d",
                "Other"
            ],
            "content":"<div class=\"\"><div> <span>\"Okay Rouge just stand here.\" He pointed to a spot on the floor. Rouge stood there and said. \"So what are you gonna try?\" \"You'll see.\" Said Tails as he fired the ray and it hit Rouge. In seconds she shrank down the 3 inches. Rouge was shocked as she looked around. everything was bigger then her! Tails picked her up and she stood on his palm. she looked like a toy in his hand. \"What did you do to me!?\" Rouge yelled. \"You said you would test my inventions.\" Said Tails smiling evily. \"Now lets run some tests.\" He took her to a hamster cage he had and put her inside. Rouge laid on the wood chip covered floor. There was even a water bottle and running wheel. Tails closed the door on the top and put a lock on it. Rouge sat here saying \"Do it for the emerald.\" Then she decided she might as well get some exercise. She got on the wheel and started running. Tails decided he wanted to.....</span></div></div>",
            "created":1582606800,
            "id":2792689,
            "title":"Mini Rouge"
        },
        "155":{
            "author_id":"babyrouge7x",
            "author_name":"Amy",
            "choices":[
                "A devise that changes IQ ",
                "Personality changer",
                "Other"
            ],
            "content":"<div class=\"\"><span style=\"font-size:1.47em;\"><div> <span>What else?</span></div></span></div>",
            "created":1582520400,
            "id":2792469,
            "title":"Other again"
        },
        "1551":{
            "author_id":"babyrouge7x",
            "author_name":"Amy",
            "choices":[
                "Falls on her bum and cries",
                "Acts like a bimbo",
                "Other"
            ],
            "content":"<div class=\"\"><span style=\"font-size:1.47em;\"><div> <span>Tails then shoots rouge in the head with a beam. Once the beam stops rouge\u2026</span></div></span></div>",
            "created":1582606800,
            "id":2792758,
            "title":" IQ "
        },
        "15511":{
            "author_id":"babyrouge7x",
            "author_name":"Amy",
            "choices":[
                "She poops",
                "Tails fed her",
                "Other"
            ],
            "content":"<div class=\"\"><span style=\"font-size:1.47em;\"><div> <span>Rouge then falls on her bum and bursts into tears. Tails picked rouge up and calmed her down. Rouge drooled as</span></div></span></div>",
            "created":1582606800,
            "id":2792762,
            "title":"Baby brain"
        },
        "155111":{
            "author_id":"babyrouge7x",
            "author_name":"Amy",
            "choices":[
                "Turned her back",
                "Changed her",
                "Other "
            ],
            "content":"<div class=\"\"><span style=\"font-size:1.47em;\"><div> <span>A bulge appeared and rouge giggled happy about the warmth. On the other hand tails found the smell terrible and </span></div></span></div>",
            "created":1582606800,
            "id":2792763,
            "title":"Baby stinks"
        },
        "1551112":{
            "author_id":"babyrouge7x",
            "author_name":"Amy",
            "choices":[
                "Shadows place",
                "Creams house",
                "Other"
            ],
            "content":"<div class=\"\"><span style=\"font-size:1.47em;\"><div> <span>Tails then changed her into a diaper and a tutu. He then put her in the stroller and decided to take her to</span></div></span></div>",
            "created":1582606800,
            "id":2792766,
            "title":"Changed her"
        },
        "15511122":{
            "author_id":"babyrouge7x",
            "author_name":"Amy",
            "choices":[
                "Made her like Rouge",
                "Apologized",
                "Other"
            ],
            "content":"<div class=\"\"><span style=\"font-size:1.47em;\"><div> <span>Once they got there vanilla opened the door and gasped in shock. \u201cYou can\u2019t just do that to someone!\u201d She yelled at tails. Tails then</span></div></span></div>",
            "created":1582606800,
            "id":2792769,
            "title":"Creams house"
        },
        "155111222":{
            "author_id":"babyrouge7x",
            "author_name":"Amy",
            "choices":[
                "Takes the device",
                "Punishes tails",
                "Other"
            ],
            "content":"<div class=\"\"><span style=\"font-size:1.47em;\"><div> <span>Tails apologized and begged vanilla to forgive him. He felt bad about it now. Vanilla wasn\u2019t having it though. \u201cYou think you can just apologize and everything will be better?\u201d She said which caused Tails to shrug. <br>\r\nVanilla then</span></div></span></div>",
            "created":1582606800,
            "id":2792774,
            "title":"Apologize "
        },
        "1553":{
            "author_id":"babyrouge7x",
            "author_name":"Amy",
            "choices":[
                "Robot nanny ",
                "Hypno Rattle",
                "Other"
            ],
            "content":"<div class=\"\"><span style=\"font-size:1.47em;\"><div> <span>What else?</span></div></span></div>",
            "created":1582606800,
            "id":2792681,
            "title":"Other"
        },
        "15533":{
            "author_id":"babyrouge7x",
            "author_name":"Amy",
            "choices":[
                "Transformation Machine",
                "VR system",
                "Other"
            ],
            "content":"<div class=\"\"><span style=\"font-size:1.47em;\"><div> <span>What else?</span></div></span></div>",
            "created":1582606800,
            "id":2792711,
            "title":"Other another time"
        },
        "155333":{
            "author_id":"babyrouge7x",
            "author_name":"Amy",
            "choices":[
                "Freeze ray",
                "Other",
                "Rouge changes her mind"
            ],
            "content":"<div class=\"\"><span style=\"font-size:1.47em;\"><div> <span>What else?</span></div></span></div>",
            "created":1582606800,
            "id":2792727,
            "title":"Other the otter"
        }
    },
    "info":{
        "author_id":"babyrouge7x",
        "author_name":"Amy",
        "brief_description":"Abdl version of Rouge the lab rat",
        "created":1582600800,
        "description":"<td align=\"left\" class=\"norm\">Tails makes a deal with Rouge. If she lets him test his inventions on her, He'll give her a chaos emerald. <br>\r\n <br>\r\nIt\u2019s the Abdl  version of this story <br>\r\n<br>\r\nOriginal: <a class=\"blue2roll\" rel=\"nofollow\" href=\"https://www.writing.com/main/interact/item_id/1555051-Rouge-The-Lab-Rat\" target=\"_blank\">https://www.writing.com/main/interact/item_id/1555051-Rouge-The-Lab-Rat</a><br>\r\n<br>\r\nDon\u2019t be shy to add :) <br>\r\n<br>\r\nYou can do anything you want as long as you follow these rules. <br>\r\n<br>\r\nRules<br>\r\n1.no vore <br>\r\n2.endings are ok<br>\r\n3. Keep characters in character <br>\r\n4. Have fun </td>",
        "id":2213920,
        "image_url":"https://images.Writing.Com/imgs/writing.com/writers/listing-header-5000.gif",
        "modified":1582663560,
        "pretty_title":"Rouge the lab rat Abdl "
    }
}