{
    "chapters":{
        "1":{
            "author_id":"rosenheim34",
            "author_name":"rosenheimer",
            "choices":[
                "arrive in time",
                "arrive but late",
                "on the way",
                "what about this Derek guy",
                "misc"
            ],
            "content":"<div class=\"\"><div> <span>Meredith Grey just finished her medical exam in Boston and moved to Seattle to get her first job assignment as assistance doctor in Seattle Grace Hospital. Also she grown up in Seattle and so can return to her hometown and also take care of her mother, who is suffering from Alzheimer.<br>\r\nHer mother was a well known and very respected surgeon.<br>\r\nOur fanfiction as well as the real TV show starts on the morning, where she has her first day at the new job. She had a one night stand with a handsome guy. She only knew his name, Derek, but what more you need to know from a one night stand. They met in a bar the night before and had some drinks together and so one thing was leading to another.<br>\r\nBut now she has to get rid of him and rush to the hospital to not be late for on her first day.<br>\r\n</span></div></div>",
            "created":1600761960,
            "id":2907866,
            "title":"start"
        }
    },
    "info":{
        "author_id":"rosenheim34",
        "author_name":"rosenheimer",
        "brief_description":"since nothing for this seems to be here",
        "created":1600761300,
        "description":"<td align=\"left\" class=\"norm\">I don't own any rights on this one, but it want to try an interactive here</td>",
        "id":2232955,
        "image_url":"https://images.Writing.Com/imgs/writing.com/writers/listing-header-5000.gif",
        "last_full_update":1600761960,
        "modified":1600761960,
        "pretty_title":"grey's anatomy fanfiction"
    }
}