{
    "chapters":{
        "1":{
            "author_id":"worker1398",
            "author_name":"Clear Diamond",
            "choices":[
                "Male",
                "Female",
                "Reserved",
                "Reserved",
                "Reserved"
            ],
            "content":"<div class=\"\"><span style=\"font-size:1.47em;\"><div> <span>You goto bed dreading the next day knowing its gonna be hell because you got fired from your job and haven't told your family. But when you wake up you relize you are shrunk and in a Disney show/movie.<br>\r\n<br>\r\nBut first what are you?</span></div></span></div>",
            "created":1591678800,
            "id":2848790,
            "title":"The Beginning...."
        },
        "11":{
            "author_id":"worker1398",
            "author_name":"Clear Diamond",
            "choices":[
                "TV Show",
                "Movie",
                "Cartoon short",
                "Video game",
                "Reserved"
            ],
            "content":"<div class=\"\"><span style=\"font-size:1.47em;\"><div> <span>Where do you find yourself?</span></div></span></div>",
            "created":1591678800,
            "id":2848792,
            "title":"Male"
        },
        "111":{
            "author_id":"worker1398",
            "author_name":"Clear Diamond",
            "choices":[
                "Gravity Falls",
                "Star vs The Forces of Evil",
                "More choices"
            ],
            "content":"<div class=\"\"><span style=\"font-size:1.47em;\"><div> <span>So you are in a Disney tv show.... But what one?</span></div></span></div>",
            "created":1591678800,
            "id":2848794,
            "title":"TV Show"
        },
        "1113":{
            "author_id":"worker1398",
            "author_name":"Clear Diamond",
            "choices":[
                "Shake it Up",
                "Kickin' It",
                "More choices"
            ],
            "content":"<div class=\"\"><span style=\"font-size:1.47em;\"><div> <span>More shows</span></div></span></div>",
            "created":1591678800,
            "id":2848795,
            "title":"More choices"
        },
        "11133":{
            "author_id":"worker1398",
            "author_name":"Clear Diamond",
            "choices":[
                "Austin and Ally",
                "Wizards of Waverly Place",
                "More choices"
            ],
            "content":"<div class=\"\"><span style=\"font-size:1.47em;\"><div> <span>More names</span></div></span></div>",
            "created":1591678800,
            "id":2848796,
            "title":"More choices"
        },
        "111333":{
            "author_id":"worker1398",
            "author_name":"Clear Diamond",
            "choices":[
                "Kim Possible",
                "Phineas and Ferb",
                "More choices"
            ],
            "content":"<div class=\"\"><span style=\"font-size:1.47em;\"><div> <span>More!!!...</span></div></span></div>",
            "created":1591678800,
            "id":2848797,
            "title":"More choices"
        },
        "1113333":{
            "author_id":"worker1398",
            "author_name":"Clear Diamond",
            "choices":[
                "Lab Rats",
                "Amphibia",
                "More choices"
            ],
            "content":"<div class=\"\"><span style=\"font-size:1.47em;\"><div> <span>More......</span></div></span></div>",
            "created":1591678800,
            "id":2848799,
            "title":"More choices"
        },
        "11133333":{
            "author_id":"worker1398",
            "author_name":"Clear Diamond",
            "choices":[
                "The Replacements",
                "Tangled: The Series",
                "More choices"
            ],
            "content":"<div class=\"\"><span style=\"font-size:1.47em;\"><div> <span>And more...</span></div></span></div>",
            "created":1591678800,
            "id":2848800,
            "title":"More choices"
        },
        "112":{
            "author_id":"worker1398",
            "author_name":"Clear Diamond",
            "choices":[
                "Z.O.M.B.I.E.S",
                "Camp Rock",
                "More choices"
            ],
            "content":"<div class=\"\"><span style=\"font-size:1.47em;\"><div> <span>So you are in a Disney movie.. what one?</span></div></span></div>",
            "created":1591678800,
            "id":2848801,
            "title":"Movie"
        },
        "1123":{
            "author_id":"worker1398",
            "author_name":"Clear Diamond",
            "choices":[
                "Adventures in Babysitting",
                "Jump In",
                "More choices"
            ],
            "content":"<div class=\"\"><span style=\"font-size:1.47em;\"><div> <span>More choices</span></div></span></div>",
            "created":1591678800,
            "id":2848802,
            "title":"More choices"
        },
        "11233":{
            "author_id":"worker1398",
            "author_name":"Clear Diamond",
            "choices":[
                "Onward",
                "High school musical",
                "More choices"
            ],
            "content":"<div class=\"\"><span style=\"font-size:1.47em;\"><div> <span>More choices</span></div></span></div>",
            "created":1591678800,
            "id":2848806,
            "title":"More choices"
        },
        "112333":{
            "author_id":"worker1398",
            "author_name":"Clear Diamond",
            "choices":[
                "How to build a better boy",
                "Frozen 1 & 2",
                "More choices"
            ],
            "content":"<div class=\"\"><span style=\"font-size:1.47em;\"><div> <span>More choices</span></div></span></div>",
            "created":1591678800,
            "id":2848807,
            "title":"More choices"
        },
        "1123332":{
            "author_id":"worker1398",
            "author_name":"Clear Diamond",
            "choices":[
                "Frozen 1",
                "Frozen 2"
            ],
            "content":"<div class=\"\"><span style=\"font-size:1.47em;\"><div> <span>What one? </span></div></span></div>",
            "created":1591678800,
            "id":2848808,
            "title":"Frozen 1 & 2"
        },
        "1123333":{
            "author_id":"worker1398",
            "author_name":"Clear Diamond",
            "choices":[
                "Princess Protection Program",
                "Wizards of Waverly Place: The Movie",
                "More choices"
            ],
            "content":"<div class=\"\"><span style=\"font-size:1.47em;\"><div> <span>More choices</span></div></span></div>",
            "created":1591678800,
            "id":2848809,
            "title":"More choices"
        },
        "11233333":{
            "author_id":"worker1398",
            "author_name":"Clear Diamond",
            "choices":[
                "Kim Possible (new live action one)",
                "Big Hero 6",
                "More choices"
            ],
            "content":"<div class=\"\"><span style=\"font-size:1.47em;\"><div> <span>More choices</span></div></span></div>",
            "created":1591678800,
            "id":2848810,
            "title":"More choices"
        },
        "112333333":{
            "author_id":"worker1398",
            "author_name":"Clear Diamond",
            "choices":[
                "Descendants 1",
                "Descendants 2",
                "More choices"
            ],
            "content":"<div class=\"\"><span style=\"font-size:1.47em;\"><div> <span>More choices</span></div></span></div>",
            "created":1591678800,
            "id":2848811,
            "title":"More choices"
        },
        "1123333333":{
            "author_id":"worker1398",
            "author_name":"Clear Diamond",
            "choices":[
                "Descendants 3",
                "Invisible Sister",
                "More choices"
            ],
            "content":"<div class=\"\"><span style=\"font-size:1.47em;\"><div> <span>More choices</span></div></span></div>",
            "created":1591678800,
            "id":2848812,
            "title":"More choices"
        },
        "11233333333":{
            "author_id":"worker1398",
            "author_name":"Clear Diamond",
            "choices":[
                "Geek Charming",
                "Cloud 9",
                "More choices"
            ],
            "content":"<div class=\"\"><span style=\"font-size:1.47em;\"><div> <span>More choices</span></div></span></div>",
            "created":1591678800,
            "id":2848814,
            "title":"More choices"
        },
        "112333333333":{
            "author_id":"worker1398",
            "author_name":"Clear Diamond",
            "choices":[
                "Avalon High",
                "The Swap",
                "More choices"
            ],
            "content":"<div class=\"\"><span style=\"font-size:1.47em;\"><div> <span>More choices</span></div></span></div>",
            "created":1591678800,
            "id":2848815,
            "title":"More choices"
        },
        "1123333333333":{
            "author_id":"worker1398",
            "author_name":"Clear Diamond",
            "choices":[
                "Meet The Robinsons",
                "StarStruck",
                "More choices"
            ],
            "content":"<div class=\"\"><span style=\"font-size:1.47em;\"><div> <span>More choices</span></div></span></div>",
            "created":1591678800,
            "id":2848817,
            "title":"More choices"
        }
    },
    "info":{
        "author_id":"worker1398",
        "author_name":"Clear Diamond",
        "brief_description":"Shrunk and transported into a Disney movie/show",
        "created":1591747080,
        "description":"<td align=\"left\" class=\"norm\">You are yourself and you goto bed dreading the next day knowing its gonna be hell because you got fired from your job and haven't told your family. But when you wake up you relize you are shrunk and in a Disney show/movie.<br>\r\n<br>\r\n*I RESERVE THE RIGHT TO REMOVE/EDIT ANY CHAPTERS I FEEL NEED IT*<br>\r\n<br>\r\nRules:<br>\r\n* No Death. You are immortal and indestructible.<br>\r\n* No scat<br>\r\n* No Male interaction (only male is the tiny if you pick to be a male as yourself)<br>\r\n* No interaction with anyone younger than 12 years old. (In other words only interact with girls 12+)<br>\r\n* No toilet stuff<br>\r\n* If u want to add pics email me first and I will see if I will allow it.<br>\r\n* Always leave a choice to have a different path. (If needed I will edit them to make it so.)<br>\r\n* </td>",
        "id":2223978,
        "image_url":"https://www.Writing.Com/main/images/action/display_cover/id/101983.jpg",
        "last_full_update":1598773260,
        "modified":1598773260,
        "pretty_title":"Shrunk in Disney shows/movies"
    }
}